<?xml version="1.0" encoding="UTF-8" ?>
<!DOCTYPE generatorConfiguration PUBLIC "-//mybatis.org//DTD MyBatis Generator Configuration 1.0//EN" "http://mybatis.org/dtd/mybatis-generator-config_1_0.dtd" >
<generatorConfiguration>

    <properties resource="config_bonus.properties" />
    <classPathEntry location="/Users/hong/Desktop/sharelibs/mysql-connector-java-5.1.11.jar"/>
    <context id="defaultContext">
        <commentGenerator>
            <property name="suppressAllComments" value="true" />
        </commentGenerator>

        <jdbcConnection driverClass="com.mysql.jdbc.Driver" connectionURL="jdbc:mysql://localhost:3306/bonus?useUnicode=true&amp;characterEncoding=utf-8" userId="root" password="dabing" />
        <javaModelGenerator targetPackage="com.pocketmoney.model" targetProject="${outputPath}/src/" />
        <sqlMapGenerator targetPackage="orm" targetProject="${outputPath}/resources/" />
        <javaClientGenerator targetPackage="com.pocketmoney.dao" targetProject="${outputPath}/src/" type="XMLMAPPER" />


        <!--<table schema="bonus" tableName="admin" domainObjectName="Admin">-->
            <!--<generatedKey column="id" sqlStatement="MySql" identity="true" />-->
        <!--</table>-->
        <!--<table schema="bonus" tableName="operate_log" domainObjectName="OperateLog">-->
            <!--<generatedKey column="id" sqlStatement="MySql" identity="true" />-->
        <!--</table>-->
        <!--<table schema="bonus" tableName="stuff" domainObjectName="Stuff">-->
            <!--<generatedKey column="id" sqlStatement="MySql" identity="true" />-->
        <!--</table>-->
        <table schema="bonus" tableName="weekly_record" domainObjectName="WeeklyRecord">
            <generatedKey column="id" sqlStatement="MySql" identity="true" />
        </table>
    </context>
</generatorConfiguration>
